LICENSE
README.rst
setup.py
pyresparser/__init__.py
pyresparser/command_line.py
pyresparser/constants.py
pyresparser/create_spacy_corpus.py
pyresparser/custom_t.py
pyresparser/custom_train.py
pyresparser/resume_parser.py
pyresparser/utils.py
pyresparser_py3.10.egg-info/PKG-INFO
pyresparser_py3.10.egg-info/SOURCES.txt
pyresparser_py3.10.egg-info/dependency_links.txt
pyresparser_py3.10.egg-info/entry_points.txt
pyresparser_py3.10.egg-info/not-zip-safe
pyresparser_py3.10.egg-info/requires.txt
pyresparser_py3.10.egg-info/top_level.txt